{"cameraMode":{"drawMode":0,"name":"Shaded","section":"Shading Mode"},"sceneLighting":true,"audioPlay":false,"sceneViewState":{"m_AlwaysRefresh":false,"showFog":true,"showSkybox":true,"showFlares":true,"showImageEffects":true,"showParticleSystems":true,"showVisualEffectGraphs":true,"m_FxEnabled":true},"in2DMode":false,"pivot":{"x":41.27412414550781,"y":25.543766021728517,"z":-15.275291442871094},"rotation":{"x":0.03418102115392685,"y":-0.9574764966964722,"z":0.12742795050144196,"w":0.25691571831703188},"size":9.889314651489258,"orthographic":false}